{
  "name": "OpenHIM",
  "description": "A middleware component designed to ease interoperability between disparate information systems, connecting health systems simply, securely and safely.",
  "license": [
    {
      "spdx": "MPL-2.0",
      "licenseURL": "https://github.com/jembi/openhim-core-js/LICENSE"
    }
  ],
  "SDGs": [
    [
      3,
      "Good Health and Well-Being"
    ]
  ],
  "sectors": [

  ],
  "type": [
    "software"
  ],
  "repositoryURL": "https://github.com/jembi/openhim-core-js",
  "organizations": [
    {
      "name": "Jembi",
      "website": "jembi.org",
      "org_type": "owner"
    }
  ]
}